{"Node":[{"NodeType":"Company","NodeName":"1","Device":[{"id":"a","Dtype":"Mosquitto","URL":null,"Protocol":null,"ContainerName":"sub1"},{"id":"a","Dtype":"Mosquitto","URL":null,"Protocol":null,"ContainerName":"sub1"},{"id":"b","Dtype":"Mosquitto","URL":null,"Protocol":null,"ContainerName":"sub1"},{"id":"b","Dtype":"Mosquitto","URL":null,"Protocol":null,"ContainerName":"sub1"},{"id":"b","Dtype":"Mosquitto","URL":null,"Protocol":null,"ContainerName":"sub1"},{"id":"b","Dtype":"Mosquitto","URL":null,"Protocol":null,"ContainerName":"sub1"},{"id":"b","Dtype":"Mosquitto","URL":null,"Protocol":null,"ContainerName":"sub1"}]},{"NodeType":"University","NodeName":"2","Device":[{"Dtype":"Mosquitto","URL":null,"Protocol":null,"ContainerName":"sub5"}]}]}